airwallex/__init__.py
airwallex/api/__init__.py
airwallex/api/account.py
airwallex/api/account_detail.py
airwallex/api/base.py
airwallex/api/beneficiary.py
airwallex/api/financial_transaction.py
airwallex/api/invoice.py
airwallex/api/issuing_authorization.py
airwallex/api/issuing_card.py
airwallex/api/issuing_cardholder.py
airwallex/api/issuing_config.py
airwallex/api/issuing_digital_wallet_token.py
airwallex/api/issuing_transaction.py
airwallex/api/issuing_transaction_dispute.py
airwallex/api/payment.py
airwallex/client.py
airwallex/exceptions.py
airwallex/models/__init__.py
airwallex/models/account.py
airwallex/models/account_detail.py
airwallex/models/base.py
airwallex/models/beneficiary.py
airwallex/models/financial_transaction.py
airwallex/models/fx.py
airwallex/models/invoice.py
airwallex/models/issuing_authorization.py
airwallex/models/issuing_card.py
airwallex/models/issuing_cardholder.py
airwallex/models/issuing_common.py
airwallex/models/issuing_config.py
airwallex/models/issuing_digital_wallet_token.py
airwallex/models/issuing_transaction.py
airwallex/models/issuing_transaction_dispute.py
airwallex/models/payment.py
airwallex/utils.py
airwallex_sdk-0.1.1.dist-info/METADATA
airwallex_sdk-0.1.1.dist-info/WHEEL
airwallex_sdk-0.1.1.dist-info/RECORD
