Metadata-Version: 2.1
Name: airwallex-sdk
Version: 0.1.1
Summary: Unofficial Airwallex SDK for Python
License: MIT
Author: duneraccoon
Author-email: benjamincsherro@hotmail.com
Requires-Python: >=3.10,<4.0
Classifier: License :: OSI Approved :: MIT License
Classifier: Programming Language :: Python :: 3
Classifier: Programming Language :: Python :: 3.10
Classifier: Programming Language :: Python :: 3.11
Classifier: Programming Language :: Python :: 3.12
Requires-Dist: httpx (>=0.28.1,<0.29.0)
Requires-Dist: pydantic (>=2.11.3,<3.0.0)
Project-URL: Source, https://github.com/DuneRaccoon/airwallex-sdk
